{"url": "https://www.npr.org/2022/09/18/1123689544/meet-the-person-helping-newly-arrived-venezuelan-migrants-in-florida", "title": "What it's like helping newly arrived Venezuelan migrants in Florida", "authors": ["Ayesha Rascoe"], "content": "What it's like helping newly arrived Venezuelan migrants in Florida NPR's Ayesha Rascoe speaks with Felipe Sousa-Lazaballet, executive director of HOPE Community Center near Orlando, which helps newly arrived migrants in Florida.\nNational What it's like helping newly arrived Venezuelan migrants in Florida What it's like helping newly arrived Venezuelan migrants in Florida Listen \u00b7 6:32 6:32 NPR's Ayesha Rascoe speaks with Felipe Sousa-Lazaballet, executive director of HOPE Community Center near Orlando, which helps newly arrived migrants in Florida. Sponsor Message Become an NPR sponsor", "excerpt": "NPR's Ayesha Rascoe speaks with Felipe Sousa-Lazaballet, executive director of HOPE Community Center near Orlando, which helps newly arrived migrants in Florida.", "content_length": 593, "published_date": "2022-09-18T07:59:44Z", "language": "en", "domain": "www.npr.org", "media": "https://media.npr.org/include/images/facebook-default-wide.jpg?s=1400", "meta_info": {"dataset_id": "30b3f88f-9374-4c38-adce-c0bbdf781597", "dataset": "news-cc", "dataset_content_length": "66730", "warc_sourced_date": "2022-09-18T14:45:49Z", "warc_extracted_date": "2022-09-18T16:57:50Z", "warc_processed_date": "2022-09-18T17:34:24Z"}, "id": "6e519c13-be94-4d3d-8e15-10215c02e2ad", "enriched_by": "NewsFetch", "enrichment_version": "1.0", "enriched_date": "2022-10-03T22:56:39Z", "enrichment_type": "inference", "model_source": "spacy", "model_name": "en_core_web_md", "category": "ner", "entities": [{"entity": "Venezuelan", "label": "NORP", "model_label": "NORP", "confidence": 1.0, "start_offset": 37, "end_offset": 47}, {"entity": "Florida", "label": "GPE", "model_label": "GPE", "confidence": 1.0, "start_offset": 60, "end_offset": 67}, {"entity": "NPR", "label": "ORG", "model_label": "ORG", "confidence": 1.0, "start_offset": 68, "end_offset": 71}, {"entity": "Ayesha Rascoe", "label": "PERSON", "model_label": "PERSON", "confidence": 1.0, "start_offset": 74, "end_offset": 87}, {"entity": "Felipe Sousa-Lazaballet", "label": "PERSON", "model_label": "PERSON", "confidence": 1.0, "start_offset": 100, "end_offset": 123}, {"entity": "HOPE Community Center", "label": "ORG", "model_label": "ORG", "confidence": 1.0, "start_offset": 147, "end_offset": 168}, {"entity": "Orlando", "label": "GPE", "model_label": "GPE", "confidence": 1.0, "start_offset": 174, "end_offset": 181}, {"entity": "Florida", "label": "GPE", "model_label": "GPE", "confidence": 1.0, "start_offset": 221, "end_offset": 228}, {"entity": "Venezuelan", "label": "NORP", "model_label": "NORP", "confidence": 1.0, "start_offset": 276, "end_offset": 286}, {"entity": "Florida", "label": "GPE", "model_label": "GPE", "confidence": 1.0, "start_offset": 299, "end_offset": 306}, {"entity": "Venezuelan", "label": "NORP", "model_label": "NORP", "confidence": 1.0, "start_offset": 344, "end_offset": 354}, {"entity": "Florida", "label": "GPE", "model_label": "GPE", "confidence": 1.0, "start_offset": 367, "end_offset": 374}, {"entity": "\u00b7 6:32 6:32", "label": "DATE", "model_label": "DATE", "confidence": 1.0, "start_offset": 382, "end_offset": 393}, {"entity": "NPR", "label": "ORG", "model_label": "ORG", "confidence": 1.0, "start_offset": 394, "end_offset": 397}, {"entity": "Ayesha Rascoe", "label": "PERSON", "model_label": "PERSON", "confidence": 1.0, "start_offset": 400, "end_offset": 413}, {"entity": "Felipe Sousa-Lazaballet", "label": "PERSON", "model_label": "PERSON", "confidence": 1.0, "start_offset": 426, "end_offset": 449}, {"entity": "HOPE Community Center", "label": "ORG", "model_label": "ORG", "confidence": 1.0, "start_offset": 473, "end_offset": 494}, {"entity": "Orlando", "label": "GPE", "model_label": "GPE", "confidence": 1.0, "start_offset": 500, "end_offset": 507}, {"entity": "Florida", "label": "GPE", "model_label": "GPE", "confidence": 1.0, "start_offset": 547, "end_offset": 554}, {"entity": "NPR", "label": "ORG", "model_label": "ORG", "confidence": 1.0, "start_offset": 582, "end_offset": 585}], "entity_aggregates": [{"entity": "Venezuelan", "label": "NORP", "model_label": null, "confidence": 1.0, "count": 3}, {"entity": "Florida", "label": "GPE", "model_label": null, "confidence": 1.0, "count": 5}, {"entity": "NPR", "label": "ORG", "model_label": null, "confidence": 1.0, "count": 3}, {"entity": "Ayesha Rascoe", "label": "PERSON", "model_label": null, "confidence": 1.0, "count": 2}, {"entity": "Felipe Sousa-Lazaballet", "label": "PERSON", "model_label": null, "confidence": 1.0, "count": 2}, {"entity": "HOPE Community Center", "label": "ORG", "model_label": null, "confidence": 1.0, "count": 2}, {"entity": "Orlando", "label": "GPE", "model_label": null, "confidence": 1.0, "count": 2}, {"entity": "\u00b7 6:32 6:32", "label": "DATE", "model_label": null, "confidence": 1.0, "count": 1}], "entities_composed": null}